algohub/.DS_Store
algohub/__init__.py
algohub/algorithms/.DS_Store
algohub/algorithms/__init__.py
algohub/algorithms/ciphers/README.md
algohub/algorithms/ciphers/__init__.py
algohub/algorithms/ciphers/caesar.py
algohub/algorithms/ciphers/morse.py
algohub/algorithms/ciphers/vigenere.py
algohub/algorithms/math/README.md
algohub/algorithms/math/__init__.py
algohub/algorithms/math/arithmetic_algorithms.py
algohub/algorithms/math/function_algorithms.py
algohub/algorithms/math/geometric_algorithms.py
algohub/algorithms/numbers/README.md
algohub/algorithms/numbers/__init__.py
algohub/algorithms/numbers/digits.py
algohub/algorithms/numbers/divisors.py
algohub/algorithms/numbers/num_base_conversion.py
algohub/algorithms/numbers/primes.py
algohub/algorithms/sorting.py
algohub/algorithms/sorting_README.md
algohub/algorithms/strings/README.md
algohub/algorithms/strings/__init__.py
algohub/algorithms/strings/custom_string_sorting.py
algohub/algorithms/strings/string_analysis.py
algohub/algorithms/strings/string_manipulation.py
algohub/data/__init__.py
algohub/data/random_number.py
algohub/data/user.py
algohub/data/validation.py
algohub-0.1.0.dist-info/METADATA
algohub-0.1.0.dist-info/WHEEL
algohub-0.1.0.dist-info/RECORD
