Metadata-Version: 2.1
Name: algohub
Version: 0.1.0
Summary: 
Author: Ula
Author-email: ula.malin35@gmail.com
Requires-Python: >=3.12,<4.0
Classifier: Programming Language :: Python :: 3
Classifier: Programming Language :: Python :: 3.12
Requires-Dist: coverage (>=7.4.3,<8.0.0)
Requires-Dist: coverage-badge (>=1.1.0,<2.0.0)
Requires-Dist: mypy (>=1.8.0,<2.0.0)
Requires-Dist: pylint (>=3.1.0,<4.0.0)
Requires-Dist: pytest (>=8.0.2,<9.0.0)
Requires-Dist: pytest-html (>=4.1.1,<5.0.0)
Requires-Dist: setuptools (>=69.1.1,<70.0.0)
Requires-Dist: sphinx (>=7.2.6,<8.0.0)
Requires-Dist: sphinx-rtd-theme (>=2.0.0,<3.0.0)
